pypi_demo_mcp/__init__.py
pypi_demo_mcp/cli.py
pypi_demo_mcp/server.py
pypi_demo_mcp-0.1.0.dist-info/METADATA
pypi_demo_mcp-0.1.0.dist-info/WHEEL
pypi_demo_mcp-0.1.0.dist-info/entry_points.txt
pypi_demo_mcp-0.1.0.dist-info/RECORD
