Metadata-Version: 2.4
Name: pypi-demo-mcp
Version: 0.1.0
Summary: A demonstration MCP server that can be easily installed to Claude Desktop
Project-URL: Homepage, https://github.com/yourusername/pypi-demo-mcp
Project-URL: Repository, https://github.com/yourusername/pypi-demo-mcp
Project-URL: Issues, https://github.com/yourusername/pypi-demo-mcp/issues
Author-email: Your Name <your.email@example.com>
License: MIT
Keywords: ai,claude,fastmcp,mcp,model-context-protocol
Classifier: Development Status :: 4 - Beta
Classifier: Intended Audience :: Developers
Classifier: License :: OSI Approved :: MIT License
Classifier: Operating System :: OS Independent
Classifier: Programming Language :: Python :: 3
Classifier: Programming Language :: Python :: 3.10
Classifier: Programming Language :: Python :: 3.11
Classifier: Programming Language :: Python :: 3.12
Classifier: Programming Language :: Python :: 3.13
Classifier: Topic :: Software Development :: Libraries :: Python Modules
Requires-Python: >=3.10
Requires-Dist: fastmcp>=2.10.2
Provides-Extra: dev
Requires-Dist: black>=22.0; extra == 'dev'
Requires-Dist: flake8>=4.0; extra == 'dev'
Requires-Dist: mypy>=0.900; extra == 'dev'
Requires-Dist: pytest>=7.0; extra == 'dev'
